<?xml version="1.0" encoding="UTF-8"?>
<bank>
<checkSum>
<noOfInvoices>11</noOfInvoices>
<noOfShippingBills>11</noOfShippingBills>
</checkSum>
<shippingBills>
<shippingBill>
<portCode>INNSA1</portCode>
<exportType>1</exportType>
<recordIndicator>1</recordIndicator>
<shippingBillNo>3055546</shippingBillNo>
<shippingBillDate>25/07/2022</shippingBillDate>
<formNo></formNo>
<LEODate>26/07/2022</LEODate>
<adCode>6770001</adCode>
<paymentSequence>3055546ITT038845</paymentSequence>
<IRMNumber>ITT792038845</IRMNumber>
<FIRCNumber></FIRCNumber>
<remittanceAdCode>6770001</remittanceAdCode>
<thirdParty>N</thirdParty>
<realizedCurrencyCode>USD</realizedCurrencyCode>
<realizationDate>08/01/2024</realizationDate>
<invoices>
<invoice>
<invoiceSerialNo>1</invoiceSerialNo>
<invoiceNo>KR/EXP/22-23/142</invoiceNo>
<invoiceDate></invoiceDate>
<accountNumber>H10792102341</accountNumber>
<bankingChargesAmt>408.8500</bankingChargesAmt>
<FOBAmt>22939.6400</FOBAmt>
<FOBAmtIC>22939.6400</FOBAmtIC>
<freightAmt>0.0000</freightAmt>
<freightAmtIC>0.0000</freightAmtIC>
<insuranceAmt>0.0000</insuranceAmt>
<insuranceAmtIC>0.0000</insuranceAmtIC>
<remitterName></remitterName>
<remitterCountry></remitterCountry>
<closeOfBillIndicator>1</closeOfBillIndicator>
</invoice>
</invoices>
</shippingBill>
<shippingBill>
<portCode>INNSA1</portCode>
<exportType>1</exportType>
<recordIndicator>1</recordIndicator>
<shippingBillNo>3055546</shippingBillNo>
<shippingBillDate>25/07/2022</shippingBillDate>
<formNo></formNo>
<LEODate>26/07/2022</LEODate>
<adCode>6770001</adCode>
<paymentSequence>3055546ITT057728</paymentSequence>
<IRMNumber>ITT792057728</IRMNumber>
<FIRCNumber></FIRCNumber>
<remittanceAdCode>6770001</remittanceAdCode>
<thirdParty>N</thirdParty>
<realizedCurrencyCode>USD</realizedCurrencyCode>
<realizationDate>08/01/2024</realizationDate>
<invoices>
<invoice>
<invoiceSerialNo>1</invoiceSerialNo>
<invoiceNo>KR/EXP/22-23/142</invoiceNo>
<invoiceDate></invoiceDate>
<accountNumber>H10792102341</accountNumber>
<bankingChargesAmt>408.8500</bankingChargesAmt>
<FOBAmt>8130.7600</FOBAmt>
<FOBAmtIC>8130.7600</FOBAmtIC>
<freightAmt>0.0000</freightAmt>
<freightAmtIC>0.0000</freightAmtIC>
<insuranceAmt>0.0000</insuranceAmt>
<insuranceAmtIC>0.0000</insuranceAmtIC>
<remitterName></remitterName>
<remitterCountry></remitterCountry>
<closeOfBillIndicator>2</closeOfBillIndicator>
</invoice>
</invoices>
</shippingBill>
<shippingBill>
<portCode>INNSA1</portCode>
<exportType>1</exportType>
<recordIndicator>1</recordIndicator>
<shippingBillNo>5654641</shippingBillNo>
<shippingBillDate>21/10/2014</shippingBillDate>
<formNo></formNo>
<LEODate>22/10/2014</LEODate>
<adCode>6770001</adCode>
<paymentSequence>5654641ITT057728</paymentSequence>
<IRMNumber>ITT792057728</IRMNumber>
<FIRCNumber></FIRCNumber>
<remittanceAdCode>6770001</remittanceAdCode>
<thirdParty>N</thirdParty>
<realizedCurrencyCode>USD</realizedCurrencyCode>
<realizationDate>08/01/2024</realizationDate>
<invoices>
<invoice>
<invoiceSerialNo>1</invoiceSerialNo>
<invoiceNo>KR/EXP/14-15/347</invoiceNo>
<invoiceDate></invoiceDate>
<accountNumber>H10792102341</accountNumber>
<bankingChargesAmt>408.8500</bankingChargesAmt>
<FOBAmt>27490.8200</FOBAmt>
<FOBAmtIC>27490.8200</FOBAmtIC>
<freightAmt>1913.0000</freightAmt>
<freightAmtIC>1913.0000</freightAmtIC>
<insuranceAmt>18.1800</insuranceAmt>
<insuranceAmtIC>18.1800</insuranceAmtIC>
<remitterName></remitterName>
<remitterCountry></remitterCountry>
<closeOfBillIndicator>2</closeOfBillIndicator>
</invoice>
</invoices>
</shippingBill>
<shippingBill>
<portCode>INNSA1</portCode>
<exportType>1</exportType>
<recordIndicator>1</recordIndicator>
<shippingBillNo>5805464</shippingBillNo>
<shippingBillDate>29/11/2022</shippingBillDate>
<formNo></formNo>
<LEODate>30/11/2022</LEODate>
<adCode>6770001</adCode>
<paymentSequence>5805464ITT057728</paymentSequence>
<IRMNumber>ITT792057728</IRMNumber>
<FIRCNumber></FIRCNumber>
<remittanceAdCode>6770001</remittanceAdCode>
<thirdParty>N</thirdParty>
<realizedCurrencyCode>USD</realizedCurrencyCode>
<realizationDate>08/01/2024</realizationDate>
<invoices>
<invoice>
<invoiceSerialNo>1</invoiceSerialNo>
<invoiceNo>KR/EXP/22-23/440</invoiceNo>
<invoiceDate></invoiceDate>
<accountNumber>H10792102341</accountNumber>
<bankingChargesAmt>408.8500</bankingChargesAmt>
<FOBAmt>32405.2400</FOBAmt>
<FOBAmtIC>32405.2400</FOBAmtIC>
<freightAmt>0.0000</freightAmt>
<freightAmtIC>0.0000</freightAmtIC>
<insuranceAmt>0.0000</insuranceAmt>
<insuranceAmtIC>0.0000</insuranceAmtIC>
<remitterName></remitterName>
<remitterCountry></remitterCountry>
<closeOfBillIndicator>1</closeOfBillIndicator>
</invoice>
</invoices>
</shippingBill>
<shippingBill>
<portCode>INNSA1</portCode>
<exportType>1</exportType>
<recordIndicator>1</recordIndicator>
<shippingBillNo>5805464</shippingBillNo>
<shippingBillDate>29/11/2022</shippingBillDate>
<formNo></formNo>
<LEODate>30/11/2022</LEODate>
<adCode>6770001</adCode>
<paymentSequence>5805464ITT057661</paymentSequence>
<IRMNumber>ITT792057661</IRMNumber>
<FIRCNumber></FIRCNumber>
<remittanceAdCode>6770001</remittanceAdCode>
<thirdParty>N</thirdParty>
<realizedCurrencyCode>USD</realizedCurrencyCode>
<realizationDate>08/01/2024</realizationDate>
<invoices>
<invoice>
<invoiceSerialNo>1</invoiceSerialNo>
<invoiceNo>KR/EXP/22-23/440</invoiceNo>
<invoiceDate></invoiceDate>
<accountNumber>H10792102341</accountNumber>
<bankingChargesAmt>408.8500</bankingChargesAmt>
<FOBAmt>15302.1100</FOBAmt>
<FOBAmtIC>15302.1100</FOBAmtIC>
<freightAmt>0.0000</freightAmt>
<freightAmtIC>0.0000</freightAmtIC>
<insuranceAmt>0.0000</insuranceAmt>
<insuranceAmtIC>0.0000</insuranceAmtIC>
<remitterName></remitterName>
<remitterCountry></remitterCountry>
<closeOfBillIndicator>2</closeOfBillIndicator>
</invoice>
</invoices>
</shippingBill>
<shippingBill>
<portCode>INNSA1</portCode>
<exportType>1</exportType>
<recordIndicator>1</recordIndicator>
<shippingBillNo>9434563</shippingBillNo>
<shippingBillDate>20/04/2023</shippingBillDate>
<formNo></formNo>
<LEODate>21/04/2023</LEODate>
<adCode>6770001</adCode>
<paymentSequence>9434563ITT057661</paymentSequence>
<IRMNumber>ITT792057661</IRMNumber>
<FIRCNumber></FIRCNumber>
<remittanceAdCode>6770001</remittanceAdCode>
<thirdParty>N</thirdParty>
<realizedCurrencyCode>USD</realizedCurrencyCode>
<realizationDate>08/01/2024</realizationDate>
<invoices>
<invoice>
<invoiceSerialNo>1</invoiceSerialNo>
<invoiceNo>KR/EXP/23-24/18</invoiceNo>
<invoiceDate></invoiceDate>
<accountNumber>H10792102341</accountNumber>
<bankingChargesAmt>408.8500</bankingChargesAmt>
<FOBAmt>27240.9800</FOBAmt>
<FOBAmtIC>27240.9800</FOBAmtIC>
<freightAmt>0.0000</freightAmt>
<freightAmtIC>0.0000</freightAmtIC>
<insuranceAmt>0.0000</insuranceAmt>
<insuranceAmtIC>0.0000</insuranceAmtIC>
<remitterName></remitterName>
<remitterCountry></remitterCountry>
<closeOfBillIndicator>1</closeOfBillIndicator>
</invoice>
</invoices>
</shippingBill>
<shippingBill>
<portCode>INNSA1</portCode>
<exportType>1</exportType>
<recordIndicator>1</recordIndicator>
<shippingBillNo>9434563</shippingBillNo>
<shippingBillDate>20/04/2023</shippingBillDate>
<formNo></formNo>
<LEODate>21/04/2023</LEODate>
<adCode>6770001</adCode>
<paymentSequence>9434563ITT034274</paymentSequence>
<IRMNumber>ITT792034274</IRMNumber>
<FIRCNumber></FIRCNumber>
<remittanceAdCode>6770001</remittanceAdCode>
<thirdParty>N</thirdParty>
<realizedCurrencyCode>USD</realizedCurrencyCode>
<realizationDate>08/01/2024</realizationDate>
<invoices>
<invoice>
<invoiceSerialNo>1</invoiceSerialNo>
<invoiceNo>KR/EXP/23-24/18</invoiceNo>
<invoiceDate></invoiceDate>
<accountNumber>H10792102341</accountNumber>
<bankingChargesAmt>408.8500</bankingChargesAmt>
<FOBAmt>13413.2300</FOBAmt>
<FOBAmtIC>13413.2300</FOBAmtIC>
<freightAmt>0.0000</freightAmt>
<freightAmtIC>0.0000</freightAmtIC>
<insuranceAmt>0.0000</insuranceAmt>
<insuranceAmtIC>0.0000</insuranceAmtIC>
<remitterName></remitterName>
<remitterCountry></remitterCountry>
<closeOfBillIndicator>2</closeOfBillIndicator>
</invoice>
</invoices>
</shippingBill>
<shippingBill>
<portCode>INNSA1</portCode>
<exportType>1</exportType>
<recordIndicator>1</recordIndicator>
<shippingBillNo>9634663</shippingBillNo>
<shippingBillDate>28/04/2023</shippingBillDate>
<formNo></formNo>
<LEODate>29/04/2023</LEODate>
<adCode>6770001</adCode>
<paymentSequence>9634663ITT050666</paymentSequence>
<IRMNumber>ITT792050666</IRMNumber>
<FIRCNumber></FIRCNumber>
<remittanceAdCode>6770001</remittanceAdCode>
<thirdParty>N</thirdParty>
<realizedCurrencyCode>USD</realizedCurrencyCode>
<realizationDate>08/01/2024</realizationDate>
<invoices>
<invoice>
<invoiceSerialNo>1</invoiceSerialNo>
<invoiceNo>KR/EXP/23-24/26</invoiceNo>
<invoiceDate></invoiceDate>
<accountNumber>H10792102341</accountNumber>
<bankingChargesAmt>170.3700</bankingChargesAmt>
<FOBAmt>8000.0000</FOBAmt>
<FOBAmtIC>0.0000</FOBAmtIC>
<freightAmt>0.0000</freightAmt>
<freightAmtIC>0.0000</freightAmtIC>
<insuranceAmt>0.0000</insuranceAmt>
<insuranceAmtIC>0.0000</insuranceAmtIC>
<remitterName></remitterName>
<remitterCountry></remitterCountry>
<closeOfBillIndicator>1</closeOfBillIndicator>
</invoice>
</invoices>
</shippingBill>
<shippingBill>
<portCode>INNSA1</portCode>
<exportType>1</exportType>
<recordIndicator>1</recordIndicator>
<shippingBillNo>9634663</shippingBillNo>
<shippingBillDate>28/04/2023</shippingBillDate>
<formNo></formNo>
<LEODate>29/04/2023</LEODate>
<adCode>6770001</adCode>
<paymentSequence>9634663ITT056800</paymentSequence>
<IRMNumber>ITT792056800</IRMNumber>
<FIRCNumber></FIRCNumber>
<remittanceAdCode>6770001</remittanceAdCode>
<thirdParty>N</thirdParty>
<realizedCurrencyCode>USD</realizedCurrencyCode>
<realizationDate>08/01/2024</realizationDate>
<invoices>
<invoice>
<invoiceSerialNo>1</invoiceSerialNo>
<invoiceNo>KR/EXP/23-24/26</invoiceNo>
<invoiceDate></invoiceDate>
<accountNumber>H10792102341</accountNumber>
<bankingChargesAmt>170.3700</bankingChargesAmt>
<FOBAmt>14185.8800</FOBAmt>
<FOBAmtIC>0.0000</FOBAmtIC>
<freightAmt>0.0000</freightAmt>
<freightAmtIC>0.0000</freightAmtIC>
<insuranceAmt>0.0000</insuranceAmt>
<insuranceAmtIC>0.0000</insuranceAmtIC>
<remitterName></remitterName>
<remitterCountry></remitterCountry>
<closeOfBillIndicator>1</closeOfBillIndicator>
</invoice>
</invoices>
</shippingBill>
<shippingBill>
<portCode>INNSA1</portCode>
<exportType>1</exportType>
<recordIndicator>1</recordIndicator>
<shippingBillNo>9634663</shippingBillNo>
<shippingBillDate>28/04/2023</shippingBillDate>
<formNo></formNo>
<LEODate>29/04/2023</LEODate>
<adCode>6770001</adCode>
<paymentSequence>9634663ITT058547</paymentSequence>
<IRMNumber>ITT792058547</IRMNumber>
<FIRCNumber></FIRCNumber>
<remittanceAdCode>6770001</remittanceAdCode>
<thirdParty>N</thirdParty>
<realizedCurrencyCode>USD</realizedCurrencyCode>
<realizationDate>08/01/2024</realizationDate>
<invoices>
<invoice>
<invoiceSerialNo>1</invoiceSerialNo>
<invoiceNo>KR/EXP/23-24/26</invoiceNo>
<invoiceDate></invoiceDate>
<accountNumber>H10792102341</accountNumber>
<bankingChargesAmt>170.3700</bankingChargesAmt>
<FOBAmt>22000.0000</FOBAmt>
<FOBAmtIC>0.0000</FOBAmtIC>
<freightAmt>0.0000</freightAmt>
<freightAmtIC>0.0000</freightAmtIC>
<insuranceAmt>0.0000</insuranceAmt>
<insuranceAmtIC>0.0000</insuranceAmtIC>
<remitterName></remitterName>
<remitterCountry></remitterCountry>
<closeOfBillIndicator>1</closeOfBillIndicator>
</invoice>
</invoices>
</shippingBill>
<shippingBill>
<portCode>INNSA1</portCode>
<exportType>1</exportType>
<recordIndicator>1</recordIndicator>
<shippingBillNo>9634663</shippingBillNo>
<shippingBillDate>28/04/2023</shippingBillDate>
<formNo></formNo>
<LEODate>29/04/2023</LEODate>
<adCode>6770001</adCode>
<paymentSequence>9634663ITT057282</paymentSequence>
<IRMNumber>ITT792057282</IRMNumber>
<FIRCNumber></FIRCNumber>
<remittanceAdCode>6770001</remittanceAdCode>
<thirdParty>N</thirdParty>
<realizedCurrencyCode>USD</realizedCurrencyCode>
<realizationDate>08/01/2024</realizationDate>
<invoices>
<invoice>
<invoiceSerialNo>1</invoiceSerialNo>
<invoiceNo>KR/EXP/23-24/26</invoiceNo>
<invoiceDate></invoiceDate>
<accountNumber>H10792102341</accountNumber>
<bankingChargesAmt>170.3700</bankingChargesAmt>
<FOBAmt>7168.8700</FOBAmt>
<FOBAmtIC>0.0000</FOBAmtIC>
<freightAmt>0.0000</freightAmt>
<freightAmtIC>0.0000</freightAmtIC>
<insuranceAmt>0.0000</insuranceAmt>
<insuranceAmtIC>0.0000</insuranceAmtIC>
<remitterName></remitterName>
<remitterCountry></remitterCountry>
<closeOfBillIndicator>2</closeOfBillIndicator>
</invoice>
</invoices>
</shippingBill>
</shippingBills>
</bank>