<?xml version="1.0" encoding="utf-8"?>
<bank>
<checkSum>
<noOfIrm>1</noOfIrm>
</checkSum>
<remittances>
<remittance>
<IRMNumber>ITT792064369</IRMNumber>
<remittanceAmount>275000.0000</remittanceAmount>
<remittanceDate>27/12/2023</remittanceDate>
<adCode>6770001</adCode>
<fircFlag>N</fircFlag>
<fircNumber></fircNumber>
<fircIssueDate></fircIssueDate>
<fircAmount></fircAmount>
<currency>USD</currency>
<ieCode>0814003836</ieCode>
<ieName>CHUKAN BUTSU EXIM INDIA PVT.LTD.</ieName>
<remitterName>UAB TOYO INK EUROPE BALTICA</remitterName>
<remitterAddress></remitterAddress>
<remitterCountry>CN</remitterCountry>
<remitterBankName>CHINA CONSTRUCTION BANK CORPORATION</remitterBankName>
<remitterBankCountry>CN</remitterBankCountry>
<swiftOtherBankRefNumber>PCBCCNBJJSS</swiftOtherBankRefNumber>
<purposeOfRemittance>P0103</purposeOfRemittance>
<recordIndicator>1</recordIndicator>
<remarks></remarks>
</remittance>
</remittances>
</bank>
